Workbook

Sheet data (1)
A1: DR_Dat | B1: DR_Tim | C1: DR_NChk | D1: DR_NDoc | E1: DR_Apt | F1: DR_Kkm | G1: DR_TDoc | H1: DR_TPay | I1: DR_CDrugs | J1: DR_NDrugs | K1: DR_Suppl | L1: DR_Prod | M1: DR_Kol | N1: DR_CZak | O1: DR_CRoz | P1: DR_SDisc | Q1: DR_CDisc | R1: DR_BCDisc | S1: DR_TabEmpl | T1: DR_VZak | U1: DR_Pos | V1: DR_Revenue
A2: 44774 | B2: 0.33770833 | C2: 1272 | D2: 13002561 | E2: 13 | F2: 22589 | G2: Розничная реализация | H2: 18 | I2: 144734 | J2: ГАСТАЛ №12 ТАБ. Д/РАСС. | K2: Пульс | L2: TEVA Pharvaceutical Industries Ltd | M2: 1 | N2: 196.71 | O2: 270 | P2: 0 | Q2: NULL | R2: NULL | S2: 29 | T2: 1 | U2: 1 | V2: =O2*M2 -> 270
A3: 44774 | B3: 0.36033565 | C3: 1273 | D3: 13002561 | E3: 13 | F3: 22589 | G3: Розничная реализация | H3: 15 | I3: 69661 | J3: ТОБРОПТ 0,3% 5МЛ. №1 ГЛ.КАПЛИ ФЛ./КАП. /РОМФАРМ/ | K3: Пульс | L3: РОМФАРМ КОМПАНИ ( ROMPHARM ) | M3: 1 | N3: 106.21 | O3: 127 | P3: 6 | Q3: 9 | R3: 200010004357 | S3: 29 | T3: 1 | U3: 1 | V3: =O3*M3 -> 127
A4: 44774 | B4: 0.37196759 | C4: 1274 | D4: 13002561 | E4: 13 | F4: 22589 | G4: Розничная реализация | H4: 18 | I4: 190635 | J4: ЭЛИКВИС 5МГ. №60 ТАБ. П/П/О /ПФАЙЗЕР/БРИСТОЛ-МАЙЕРС/ | K4: ГРАНД КАПИТАЛ СМОЛЕНСК ООО ФК | L4: Пфайзер | M4: 1 | N4: 2320.99 | O4: 2563 | P4: 76 | Q4: 9 | R4: 200010018491 | S4: 29 | T4: 1 | U4: 1 | V4: =O4*M4 -> 2563
A5: 44774 | B5: 0.37546296 | C5: 1275 | D5: 13002561 | E5: 13 | F5: 22589 | G5: Розничная реализация | H5: 18 | I5: 276370 | J5: АРБИДОЛ МАКСИМУМ 200МГ. №10 КАПС. /ОТИСИФАРМ/ФАРМСТАНДАРТ/ | K5: Пульс | L5: ОТИСИФАРМ ПАО | M5: 1 | N5: 445.39 | O5: 541 | P5: 0 | Q5: NULL | R5: NULL | S5: 29 | T5: 1 | U5: 1 | V5: =O5*M5 -> 541 | X5: =MIN(A:A) -> 44774
A6: 44774 | B6: 0.37783565 | C6: 1276 | D6: 13002561 | E6: 13 | F6: 22589 | G6: Розничная реализация | H6: 15 | I6: 2303 | J6: ЭНАМ 2,5МГ. №20 ТАБ. /Д-Р РЕДДИ/ | K6: Протек | L6: Д-р Редди с Лабораторис Лтд / Dr.REDDY's | M6: 1 | N6: 18.04 | O6: 22 | P6: 1 | Q6: 9 | R6: 200010000734 | S6: 29 | T6: 1 | U6: 5 | V6: =O6*M6 -> 22 | X6: =MAX(A:A) -> 44778
A7: 44774 | B7: 0.37783565 | C7: 1276 | D7: 13002561 | E7: 13 | F7: 22589 | G7: Розничная реализация | H7: 15 | I7: 2303 | J7: ЭНАМ 2,5МГ. №20 ТАБ. /Д-Р РЕДДИ/ | K7: Протек | L7: Д-р Редди с Лабораторис Лтд / Dr.REDDY's | M7: 1 | N7: 18.04 | O7: 22 | P7: 1 | Q7: 9 | R7: 200010000734 | S7: 29 | T7: 1 | U7: 6 | V7: =O7*M7 -> 22
A8: 44774 | B8: 0.37783565 | C8: 1276 | D8: 13002561 | E8: 13 | F8: 22589 | G8: Розничная реализация | H8: 15 | I8: 338588 | J8: КЛОПИДОГРЕЛ-СЗ 75МГ. №28 ТАБ. П/П/О /СЕВЕРНАЯ ЗВЕЗДА/ | K8: Пульс | L8: Северная Звезда | M8: 1 | N8: 383.7 | O8: 475 | P8: 23 | Q8: 9 | R8: 200010000734 | S8: 29 | T8: 1 | U8: 3 | V8: =O8*M8 -> 475
A9: 44774 | B9: 0.37783565 | C9: 1276 | D9: 13002561 | E9: 13 | F9: 22589 | G9: Розничная реализация | H9: 15 | I9: 397616 | J9: КО-ВАМЛОСЕТ 5МГ.+160МГ.+12,5МГ. №30 ТАБ. П/П/О | K9: Протек | L9: КРКА-Рус ООО (KRKA ) | M9: 1 | N9: 536.82 | O9: 693 | P9: 48 | Q9: 9 | R9: 200010000734 | S9: 29 | T9: 1 | U9: 4 | V9: =O9*M9 -> 693
A10: 44774 | B10: 0.37783565 | C10: 1276 | D10: 13002561 | E10: 13 | F10: 22589 | G10: Розничная реализация | H10: 15 | I10: 338492 | J10: АТОРВАСТАТИН-СЗ 20МГ. №60 ТАБ. П/П/О /СЕВЕРНАЯ ЗВЕЗДА/ | K10: Протек | L10: Северная Звезда | M10: 1 | N10: 334.29 | O10: 418 | P10: 20 | Q10: 9 | R10: 200010000734 | S10: 29 | T10: 1 | U10: 1 | V10: =O10*M10 -> 418
A11: 44774 | B11: 0.37783565 | C11: 1276 | D11: 13002561 | E11: 13 | F11: 22589 | G11: Розничная реализация | H11: 15 | I11: 338479 | J11: АТОРВАСТАТИН-СЗ 40МГ. №30 ТАБ. П/П/О /СЕВЕРНАЯ ЗВЕЗДА/ | K11: Пульс | L11: Северная Звезда | M11: 1 | N11: 282.52 | O11: 340 | P11: 17 | Q11: 9 | R11: 200010000734 | S11: 29 | T11: 1 | U11: 2 | V11: =O11*M11 -> 340
A12: 44774 | B12: 0.37849537 | C12: 1277 | D12: 13002561 | E12: 13 | F12: 22589 | G12: Розничная реализация | H12: 18 | I12: 122156 | J12: КСИМЕЛИН ЭКСТРА 84МКГ/ДОЗА+70МКГ/ДОЗА 10МЛ. №1 НАЗАЛ.СПРЕЙ ДОЗИР. ФЛ. | K12: Пульс | L12: ТАКЕДА ФАРМАСЬЮТИКАЛ КОМПАНИ ЛИМИТЕД | M12: 1 | N12: 210.25 | O12: 284 | P12: 0 | Q12: NULL | R12: NULL | S12: 29 | T12: 1 | U12: 1 | V12: =O12*M12 -> 284
A13: 44774 | B13: 0.38320602 | C13: 1278 | D13: 13002561 | E13: 13 | F13: 22589 | G13: Розничная реализация | H13: 15 | I13: 608487 | J13: NF ВАТА ХИРУРГ. СТЕР. 100Г. /НЬЮФАРМ/ | K13: Фармкомплект ООО | L13: НьюФарм | M13: 1 | N13: 43.29 | O13: 71 | P13: 7 | Q13: 9 | R13: 200010001758 | S13: 29 | T13: 1 | U13: 1 | V13: =O13*M13 -> 71
A14: 44774 | B14: 0.38320602 | C14: 1278 | D14: 13002561 | E14: 13 | F14: 22589 | G14: Розничная реализация | H14: 15 | I14: 528004 | J14: СТОПСЕПТ ПЛЮС 90% 100МЛ. ДЕЗ.СР-ВО ФЛ. | K14: Авеста | L14: ГИППОКРАТ ООО | M14: 1 | N14: 35.52 | O14: 58 | P14: 5 | Q14: 9 | R14: 200010001758 | S14: 29 | T14: 1 | U14: 2 | V14: =O14*M14 -> 58
A15: 44774 | B15: 0.38756944 | C15: 1279 | D15: 13002561 | E15: 13 | F15: 22589 | G15: Розничная реализация | H15: 15 | I15: 443174 | J15: ПАСКАЛЬ ШПРИЦ 3-Х КОМП. 2МЛ. С ИГЛОЙ 23G 0,6Х30ММ. №10 [PASCAL] | K15: Катрен г.Химки | L15: ПАСКАЛЬ МЕДИКАЛ | M15: 1 | N15: 65.13 | O15: 103 | P15: 0 | Q15: NULL | R15: NULL | S15: 29 | T15: 1 | U15: 1 | V15: =O15*M15 -> 103
A16: 44774 | B16: 0.44326389 | C16: 1294 | D16: 13002561 | E16: 13 | F16: 22589 | G16: Розничная реализация | H16: 18 | I16: 443174 | J16: ПАСКАЛЬ ШПРИЦ 3-Х КОМП. 2МЛ. С ИГЛОЙ 23G 0,6Х30ММ. №10 [PASCAL] | K16: Катрен г.Химки | L16: ПАСКАЛЬ МЕДИКАЛ | M16: 1 | N16: 65.13 | O16: 103 | P16: 0 | Q16: NULL | R16: NULL | S16: 29 | T16: 1 | U16: 3 | V16: =O16*M16 -> 103
A17: 44774 | B17: 0.39586806 | C17: 1280 | D17: 13002561 | E17: 13 | F17: 22589 | G17: Розничная реализация | H17: 15 | I17: 21372 | J17: КЛОТРИМАЗОЛ 1% 20Г. КРЕМ Д/НАРУЖ.ПРИМ. ТУБА /ХИПЕРИОН/РУМЫНИЯ/ | K17: Пульс | L17: HYPERION SA (ХИПЕРИОН ) | M17: 1 | N17: 86.28 | O17: 123 | P17: 0 | Q17: NULL | R17: NULL | S17: 29 | T17: 1 | U17: 1 | V17: =O17*M17 -> 123
A18: 44774 | B18: 0.39586806 | C18: 1280 | D18: 13002561 | E18: 13 | F18: 22589 | G18: Розничная реализация | H18: 15 | I18: 365627 | J18: РИНОНОРМ-ТЕВА 0,1% 140МКГ/ДОЗА 20МЛ. НАЗАЛ.СПРЕЙ ФЛ. /ТЕВА/ | K18: ГРАНД КАПИТАЛ СМОЛЕНСК ООО ФК | L18: ТЕВА ЧЕШСКОЕ ПРЕДПРИЯТИЕ | M18: 1 | N18: 78.24 | O18: 96 | P18: 0 | Q18: NULL | R18: NULL | S18: 29 | T18: 1 | U18: 2 | V18: =O18*M18 -> 96
A19: 44774 | B19: 0.68071759 | C19: 1373 | D19: 13002561 | E19: 13 | F19: 22589 | G19: Розничная реализация | H19: 18 | I19: 365627 | J19: РИНОНОРМ-ТЕВА 0,1% 140МКГ/ДОЗА 20МЛ. НАЗАЛ.СПРЕЙ ФЛ. /ТЕВА/ | K19: ГРАНД КАПИТАЛ СМОЛЕНСК ООО ФК | L19: ТЕВА ЧЕШСКОЕ ПРЕДПРИЯТИЕ | M19: 1 | N19: 78.24 | O19: 96 | P19: 0 | Q19: NULL | R19: NULL | S19: 29 | T19: 1 | U19: 1 | V19: =O19*M19 -> 96
A20: 44774 | B20: 0.40825231 | C20: 1281 | D20: 13002561 | E20: 13 | F20: 22589 | G20: Розничная реализация | H20: 15 | I20: 12625 | J20: ДЮФАЛАК 667МГ/МЛ. 500МЛ. СИРОП ФЛ. +МЕРН.СТАКАН /ЭББОТТ/СОЛВЕЙ/ | K20: Арал плюс | L20: Abbott Japan Co ( ЭББОТТ ) | M20: 1 | N20: 455.9 | O20: 553 | P20: 16 | Q20: 9 | R20: 200010001617 | S20: 29 | T20: 1 | U20: 1 | V20: =O20*M20 -> 553
A21: 44774 | B21: 0.41150463 | C21: 1282 | D21: 13002561 | E21: 13 | F21: 22589 | G21: Розничная реализация | H21: 18 | I21: 67565 | J21: ГЕЛАДРИНК ФОРТЕ ПОР. Д/ПРИЕМА ВНУТРЬ АПЕЛЬСИН 420Г. БАНКА | K21: ВИТТА КОМПАНИ ООО | L21: ОРЛИНГ | M21: 1 | N21: 3638.1 | O21: 4985 | P21: 498 | Q21: 9 | R21: 200010004830 | S21: 29 | T21: 1 | U21: 1 | V21: =O21*M21 -> 4985
A22: 44774 | B22: 0.41150463 | C22: 1282 | D22: 13002561 | E22: 13 | F22: 22589 | G22: Розничная реализация | H22: 18 | I22: 507949 | J22: ПИРАЦЕТАМ 200МГ. №60 ТАБ. П/П/О /ОБНОВЛЕНИЕ/ | K22: ГК Надежда Фарм | L22: ОБНОВЛЕНИЕ ПФК | M22: 1 | N22: 60.22 | O22: 73 | P22: 3 | Q22: 9 | R22: 200010004830 | S22: 29 | T22: 1 | U22: 2 | V22: =O22*M22 -> 73
A23: 44774 | B23: 0.4140162 | C23: 1283 | D23: 13002561 | E23: 13 | F23: 22589 | G23: Розничная реализация | H23: 15 | I23: 461654 | J23: МАГНЕЛИС В6 №120 ТАБ. П/О | K23: Катрен г.Химки | L23: ФАРМСТАНДАРТ УФАВИТА | M23: 1 | N23: 677.2 | O23: 779 | P23: 54 | Q23: 9 | R23: 200010020913 | S23: 29 | T23: 1 | U23: 2 | V23: =O23*M23 -> 779
A24: 44774 | B24: 0.4140162 | C24: 1283 | D24: 13002561 | E24: 13 | F24: 22589 | G24: Розничная реализация | H24: 15 | I24: 7697 | J24: МЕЗИМ-ФОРТЕ №80 ТАБ. П/О /БЕРЛИН-ХЕМИ/ | K24: Пульс | L24: Берлин-Хеми АГ/Менарини Групп (Menarini ) | M24: 1 | N24: 248.34 | O24: 302 | P24: 15 | Q24: 9 | R24: 200010020913 | S24: 29 | T24: 1 | U24: 3 | V24: =O24*M24 -> 302
A25: 44774 | B25: 0.4140162 | C25: 1283 | D25: 13002561 | E25: 13 | F25: 22589 | G25: Розничная реализация | H25: 15 | I25: 340968 | J25: КАЛЬЦИЙ Д3 НИКОМЕД 500МГ.+200МЕ №60 КЛУБНИКА+АРБУЗ ТАБ.ЖЕВ. | K25: Пульс | L25: ТАКЕДА ФАРМАСЬЮТИКАЛ КОМПАНИ ЛИМИТЕД | M25: 1 | N25: 403.68 | O25: 533 | P25: 37 | Q25: 9 | R25: 200010020913 | S25: 29 | T25: 1 | U25: 1 | V25: =O25*M25 -> 533
A26: 44774 | B26: 0.41548611 | C26: 1284 | D26: 13002561 | E26: 13 | F26: 22589 | G26: Розничная реализация | H26: 15 | I26: 530607 | J26: ЭКСПРЕСС-ТЕСТ НА А/ТЕЛА COVID-19 LGG/LGM | K26: Арал плюс | L26: ИМТЭК ООО | M26: 2 | N26: 619.88 | O26: 862 | P26: 172 | Q26: 9 | R26: 200010017394 | S26: 29 | T26: 1 | U26: 1 | V26: =O26*M26 -> 1724
A27: 44774 | B27: 0.41795139 | C27: 1285 | D27: 13002561 | E27: 13 | F27: 22589 | G27: Розничная реализация | H27: 18 | I27: 330172 | J27: БОБС ЛЕДЕНЦЫ Д/ГОРЛА 35Г. ЭКСТРА МЕНТОЛ №10 | K27: Протек | L27: МАК-ИВАНОВО | M27: 1 | N27: 23.98 | O27: 39 | P27: 0 | Q27: NULL | R27: NULL | S27: 29 | T27: 1 | U27: 1 | V27: =O27*M27 -> 39
A28: 44774 | B28: 0.41947917 | C28: 1286 | D28: 13002561 | E28: 13 | F28: 22589 | G28: Розничная реализация | H28: 18 | I28: 393315 | J28: ЦИТРАМОН П №10 ТАБ. /ФАРМСТАНДАРТ/ | K28: Катрен г.Химки | L28: ФАРМСТАНДАРТ ЛЕКСРЕДСТВА ОАО | M28: 1 | N28: 16.21 | O28: 25 | P28: 0 | Q28: NULL | R28: NULL | S28: 29 | T28: 1 | U28: 1 | V28: =O28*M28 -> 25
A29: 44774 | B29: 0.41947917 | C29: 1286 | D29: 13002561 | E29: 13 | F29: 22589 | G29: Розничная реализация | H29: 18 | I29: 393315 | J29: ЦИТРАМОН П №10 ТАБ. /ФАРМСТАНДАРТ/ | K29: Катрен г.Химки | L29: ФАРМСТАНДАРТ ЛЕКСРЕДСТВА ОАО | M29: 1 | N29: 16.21 | O29: 25 | P29: 0 | Q29: NULL | R29: NULL | S29: 29 | T29: 1 | U29: 2 | V29: =O29*M29 -> 25
A30: 44774 | B30: 0.62164352 | C30: 1362 | D30: 13002561 | E30: 13 | F30: 22589 | G30: Розничная реализация | H30: 18 | I30: 393315 | J30: ЦИТРАМОН П №10 ТАБ. /ФАРМСТАНДАРТ/ | K30: Катрен г.Химки | L30: ФАРМСТАНДАРТ ЛЕКСРЕДСТВА ОАО | M30: 1 | N30: 16.21 | O30: 25 | P30: 0 | Q30: NULL | R30: NULL | S30: 29 | T30: 1 | U30: 3 | V30: =O30*M30 -> 25
A31: 44774 | B31: 0.42930556 | C31: 1287 | D31: 13002561 | E31: 13 | F31: 22589 | G31: Розничная реализация | H31: 18 | I31: 377588 | J31: ТИЗИН КЛАССИК 0,1% 10МЛ. НАЗАЛ.СПРЕЙ ФЛ. /ДЖОНСОН/ | K31: Катрен г.Химки | L31: ДЕЛЬФАРМ ОРЛЕАН ( DELPHARM ) | M31: 1 | N31: 84.17 | O31: 100 | P31: 41.09 | Q31: 925 | R31: 200000000492 | S31: 29 | T31: 1 | U31: 3 | V31: =O31*M31 -> 100
A32: 44774 | B32: 0.42930556 | C32: 1287 | D32: 13002561 | E32: 13 | F32: 22589 | G32: Розничная реализация | H32: 18 | I32: 297336 | J32: ЛАКОМКА ПОМАДА ГИГИЕН. ЯГОДНЫЙ МИКС 2,8Г. /АВАНТА/ | K32: Протек | L32: АВАНТА ОАО | M32: 1 | N32: 45.17 | O32: 74 | P32: 30.41 | Q32: 925 | R32: 200000000492 | S32: 29 | T32: 1 | U32: 1 | V32: =O32*M32 -> 74
A33: 44774 | B33: 0.42930556 | C33: 1287 | D33: 13002561 | E33: 13 | F33: 22589 | G33: Розничная реализация | H33: 18 | I33: 2302 | J33: ОМЕЗ 20МГ. №30 КАПС. /Д-Р РЕДДИ/ | K33: ВИТТА КОМПАНИ ООО | L33: ДОКТОР РЕДДИ С ЛАБ / Dr. REDDY's ) | M33: 1 | N33: 148.28 | O33: 174 | P33: 71.5 | Q33: 925 | R33: 200000000492 | S33: 29 | T33: 1 | U33: 2 | V33: =O33*M33 -> 174
A34: 44774 | B34: 0.43451389 | C34: 1288 | D34: 13002561 | E34: 13 | F34: 22589 | G34: Розничная реализация | H34: 15 | I34: 23396 | J34: ЭВКАЛИПТ М №24 ПАСТИЛКИ | K34: ООО "Акцентмед" | L34: ДР.АУФДЕРМАУР АГ | M34: 2 | N34: 248.26 | O34: 336 | P34: 0 | Q34: NULL | R34: NULL | S34: 29 | T34: 1 | U34: 1 | V34: =O34*M34 -> 672
A35: 44774 | B35: 0.43633102 | C35: 1289 | D35: 13002561 | E35: 13 | F35: 22589 | G35: Розничная реализация | H35: 15 | I35: 143150 | J35: АЗАРГА 10МГ/МЛ.+5МГ/МЛ. 5МЛ. №1 ГЛ.КАПЛИ ФЛ./КАП. | K35: ВИТТА КОМПАНИ ООО | L35: АЛКОН Куврер н.в. (ALCON ) | M35: 1 | N35: 1042.25 | O35: 1314 | P35: 91 | Q35: 9 | R35: 200010000065 | S35: 29 | T35: 1 | U35: 1 | V35: =O35*M35 -> 1314
A36: 44774 | B36: 0.43633102 | C36: 1289 | D36: 13002561 | E36: 13 | F36: 22589 | G36: Розничная реализация | H36: 15 | I36: 263189 | J36: ТРАВАТАН 0,004% 2,5МЛ. №3 ГЛ.КАПЛИ ФЛ./КАП. | K36: Катрен г.Химки | L36: ALCON COUVREUR (АЛКОН ) | M36: 1 | N36: 1576.65 | O36: 1971 | P36: 137 | Q36: 9 | R36: 200010000065 | S36: 29 | T36: 1 | U36: 5 | V36: =O36*M36 -> 1971
A37: 44774 | B37: 0.43633102 | C37: 1289 | D37: 13002561 | E37: 13 | F37: 22589 | G37: Розничная реализация | H37: 15 | I37: 519407 | J37: ЙОДА 5% 10МЛ. СПИРТ. Р-Р ФЛ. /ЯРОСЛАВСКАЯ ФФ/ | K37: Катрен г.Химки | L37: ЯРОСЛАВСКАЯ ФАРМ. ФАБРИКА | M37: 1 | N37: 34.25 | O37: 53 | P37: 3 | Q37: 9 | R37: 200010000065 | S37: 29 | T37: 1 | U37: 2 | V37: =O37*M37 -> 53
A38: 44774 | B38: 0.43633102 | C38: 1289 | D38: 13002561 | E38: 13 | F38: 22589 | G38: Розничная реализация | H38: 15 | I38: 345211 | J38: ОМЕПРАЗОЛ 20МГ. №30 КАПС. /ПРОИЗВОДСТВО МЕДИКАМЕНТОВ/ | K38: ГРАНД КАПИТАЛ СМОЛЕНСК ООО ФК | L38: ПРОИЗВОДСТВО МЕДИКАМЕНТОВ ООО | M38: 1 | N38: 25.28 | O38: 30 | P38: 1 | Q38: 9 | R38: 200010000065 | S38: 29 | T38: 1 | U38: 3 | V38: =O38*M38 -> 30
A39: 44774 | B39: 0.47800926 | C39: 1307 | D39: 13002561 | E39: 13 | F39: 22589 | G39: Розничная реализация | H39: 18 | I39: 345211 | J39: ОМЕПРАЗОЛ 20МГ. №30 КАПС. /ПРОИЗВОДСТВО МЕДИКАМЕНТОВ/ | K39: ГРАНД КАПИТАЛ СМОЛЕНСК ООО ФК | L39: ПРОИЗВОДСТВО МЕДИКАМЕНТОВ ООО | M39: 1 | N39: 25.28 | O39: 30 | P39: 1 | Q39: 9 | R39: 200010000452 | S39: 29 | T39: 1 | U39: 1 | V39: =O39*M39 -> 30
A40: 44774 | B40: 0.50565972 | C40: 1319 | D40: 13002561 | E40: 13 | F40: 22589 | G40: Розничная реализация | H40: 18 | I40: 345211 | J40: ОМЕПРАЗОЛ 20МГ. №30 КАПС. /ПРОИЗВОДСТВО МЕДИКАМЕНТОВ/ | K40: ГРАНД КАПИТАЛ СМОЛЕНСК ООО ФК | L40: ПРОИЗВОДСТВО МЕДИКАМЕНТОВ ООО | M40: 1 | N40: 25.28 | O40: 30 | P40: 1 | Q40: 9 | R40: 200010015482 | S40: 29 | T40: 1 | U40: 3 | V40: =O40*M40 -> 30
A41: 44774 | B41: 0.43633102 | C41: 1289 | D41: 13002561 | E41: 13 | F41: 22589 | G41: Розничная реализация | H41: 15 | I41: 1504015 | J41: ПАКЕТ | K41: Индивидуальный предприниматель Кочанов Андрей Миха | L41: ПРОИЗВОДСТВО МЕДИКАМЕНТОВ ООО | M41: 1 | N41: 1.15 | O41: 2 | P41: 0 | Q41: NULL | R41: NULL | S41: 29 | T41: 1 | U41: 4 | V41: =O41*M41 -> 2
A42: 44774 | B42: 0.43896991 | C42: 1290 | D42: 13002561 | E42: 13 | F42: 22589 | G42: Розничная реализация | H42: 15 | I42: 1504015 | J42: ПАКЕТ | K42: Индивидуальный предприниматель Кочанов Андрей Миха | L42: ПРОИЗВОДСТВО МЕДИКАМЕНТОВ ООО | M42: 1 | N42: 1.15 | O42: 2 | P42: 0 | Q42: NULL | R42: NULL | S42: 29 | T42: 1 | U42: 4 | V42: =O42*M42 -> 2
A43: 44774 | B43: 0.44123843 | C43: 1292 | D43: 13002561 | E43: 13 | F43: 22589 | G43: Розничная реализация | H43: 18 | I43: 1504015 | J43: ПАКЕТ | K43: Индивидуальный предприниматель Кочанов Андрей Миха | L43: ПРОИЗВОДСТВО МЕДИКАМЕНТОВ ООО | M43: 1 | N43: 1.15 | O43: 2 | P43: 0 | Q43: NULL | R43: NULL | S43: 29 | T43: 1 | U43: 3 | V43: =O43*M43 -> 2
A44: 44774 | B44: 0.44861111 | C44: 1297 | D44: 13002561 | E44: 13 | F44: 22589 | G44: Розничная реализация | H44: 15 | I44: 1504015 | J44: ПАКЕТ | K44: Индивидуальный предприниматель Кочанов Андрей Миха | L44: ПРОИЗВОДСТВО МЕДИКАМЕНТОВ ООО | M44: 1 | N44: 1.15 | O44: 2 | P44: 0 | Q44: NULL | R44: NULL | S44: 29 | T44: 1 | U44: 4 | V44: =O44*M44 -> 2
A45: 44774 | B45: 0.45111111 | C45: 1298 | D45: 13002561 | E45: 13 | F45: 22589 | G45: Розничная реализация | H45: 18 | I45: 1504015 | J45: ПАКЕТ | K45: Индивидуальный предприниматель Кочанов Андрей Миха | L45: ПРОИЗВОДСТВО МЕДИКАМЕНТОВ ООО | M45: 1 | N45: 1.15 | O45: 2 | P45: 0 | Q45: NULL | R45: NULL | S45: 29 | T45: 1 | U45: 4 | V45: =O45*M45 -> 2
A46: 44774 | B46: 0.51331019 | C46: 1324 | D46: 13002561 | E46: 13 | F46: 22589 | G46: Розничная реализация | H46: 15 | I46: 1504015 | J46: ПАКЕТ | K46: Индивидуальный предприниматель Кочанов Андрей Миха | L46: ПРОИЗВОДСТВО МЕДИКАМЕНТОВ ООО | M46: 1 | N46: 1.15 | O46: 2 | P46: 0 | Q46: NULL | R46: NULL | S46: 29 | T46: 1 | U46: 2 | V46: =O46*M46 -> 2
A47: 44774 | B47: 0.5237963 | C47: 1327 | D47: 13002561 | E47: 13 | F47: 22589 | G47: Розничная реализация | H47: 18 | I47: 1504015 | J47: ПАКЕТ | K47: Индивидуальный предприниматель Кочанов Андрей Миха | L47: ПРОИЗВОДСТВО МЕДИКАМЕНТОВ ООО | M47: 1 | N47: 1.15 | O47: 2 | P47: 0 | Q47: NULL | R47: NULL | S47: 29 | T47: 1 | U47: 4 | V47: =O47*M47 -> 2
A48: 44774 | B48: 0.6430787 | C48: 1367 | D48: 13002561 | E48: 13 | F48: 22589 | G48: Розничная реализация | H48: 18 | I48: 1504015 | J48: ПАКЕТ | K48: Индивидуальный предприниматель Кочанов Андрей Миха | L48: ПРОИЗВОДСТВО МЕДИКАМЕНТОВ ООО | M48: 1 | N48: 1.15 | O48: 2 | P48: 0 | Q48: NULL | R48: NULL | S48: 29 | T48: 1 | U48: 3 | V48: =O48*M48 -> 2
A49: 44774 | B49: 0.70020833 | C49: 1380 | D49: 13002561 | E49: 13 | F49: 22589 | G49: Розничная реализация | H49: 18 | I49: 1504015 | J49: ПАКЕТ | K49: Индивидуальный предприниматель Кочанов Андрей Миха | L49: ПРОИЗВОДСТВО МЕДИКАМЕНТОВ ООО | M49: 1 | N49: 1.15 | O49: 2 | P49: 0 | Q49: NULL | R49: NULL | S49: 29 | T49: 1 | U49: 5 | V49: =O49*M49 -> 2
A50: 44774 | B50: 0.78233796 | C50: 1402 | D50: 13002561 | E50: 13 | F50: 22589 | G50: Розничная реализация | H50: 18 | I50: 1504015 | J50: ПАКЕТ | K50: Индивидуальный предприниматель Кочанов Андрей Миха | L50: ПРОИЗВОДСТВО МЕДИКАМЕНТОВ ООО | M50: 1 | N50: 1.15 | O50: 2 | P50: 0 | Q50: NULL | R50: NULL | S50: 29 | T50: 1 | U50: 5 | V50: =O50*M50 -> 2
A51: 44774 | B51: 0.43896991 | C51: 1290 | D51: 13002561 | E51: 13 | F51: 22589 | G51: Розничная реализация | H51: 15 | I51: 497302 | J51: ПЕРЕКИСЬ ВОДОРОДА 3% 100МЛ. №1 Р-Р ДЕЗ.СР-ВО ФЛ. ПЛАСТ. /САМАРАМЕДПРОМ/ | K51: Катрен г.Химки | L51: Самарамедпром ОАО | M51: 2 | N51: 9.79 | O51: 16 | P51: 3 | Q51: 9 | R51: 200010000065 | S51: 29 | T51: 1 | U51: 6 | V51: =O51*M51 -> 32
A52: 44774 | B52: 0.43896991 | C52: 1290 | D52: 13002561 | E52: 13 | F52: 22589 | G52: Розничная реализация | H52: 15 | I52: 278599 | J52: ХЕЛП БИНТ СТЕР. 7МХ14СМ И/У [HELP] | K52: Пульс | L52: ЭВТЕКС | M52: 2 | N52: 30.62 | O52: 50 | P52: 10 | Q52: 9 | R52: 200010000065 | S52: 29 | T52: 1 | U52: 8 | V52: =O52*M52 -> 100
A53: 44774 | B53: 0.43896991 | C53: 1290 | D53: 13002561 | E53: 13 | F53: 22589 | G53: Розничная реализация | H53: 15 | I53: 50279 | J53: БИНТ СТЕР. 10МХ16СМ И/У | K53: Катрен г.Химки | L53: ЭВТЕКС | M53: 1 | N53: 45.13 | O53: 74 | P53: 7 | Q53: 9 | R53: 200010000065 | S53: 29 | T53: 1 | U53: 1 | V53: =O53*M53 -> 74
A54: 44774 | B54: 0.43896991 | C54: 1290 | D54: 13002561 | E54: 13 | F54: 22589 | G54: Розничная реализация | H54: 15 | I54: 142036 | J54: ПЕНТАЛГИН №24 ТАБ. П/П/О /ОТИСИФАРМ/ | K54: Пульс | L54: ФАРМСТАНДАРТ ЛЕКСРЕДСТВА ОАО | M54: 1 | N54: 187.36 | O54: 220 | P54: 15 | Q54: 9 | R54: 200010000065 | S54: 29 | T54: 1 | U54: 5 | V54: =O54*M54 -> 220
A55: 44774 | B55: 0.52601852 | C55: 1328 | D55: 13002561 | E55: 13 | F55: 22589 | G55: Розничная реализация | H55: 15 | I55: 142036 | J55: ПЕНТАЛГИН №24 ТАБ. П/П/О /ОТИСИФАРМ/ | K55: Пульс | L55: ФАРМСТАНДАРТ ЛЕКСРЕДСТВА ОАО | M55: 1 | N55: 187.36 | O55: 220 | P55: 0 | Q55: NULL | R55: NULL | S55: 29 | T55: 1 | U55: 4 | V55: =O55*M55 -> 220
A56: 44774 | B56: 0.43896991 | C56: 1290 | D56: 13002561 | E56: 13 | F56: 22589 | G56: Розничная реализация | H56: 15 | I56: 523194 | J56: НАЙЗ АКТИВГЕЛЬ 1% 50Г. №1 ГЕЛЬ Д/НАРУЖ.ПРИМ. ТУБА | K56: ГРАНД КАПИТАЛ СМОЛЕНСК ООО ФК | L56: Д-р Редди с Лабораторис Лтд / Dr.REDDY's | M56: 1 | N56: 320.39 | O56: 423 | P56: 29 | Q56: 9 | R56: 200010000065 | S56: 29 | T56: 1 | U56: 3 | V56: =O56*M56 -> 423
A57: 44774 | B57: 0.43896991 | C57: 1290 | D57: 13002561 | E57: 13 | F57: 22589 | G57: Розничная реализация | H57: 15 | I57: 460183 | J57: ГУБКА ГЕМОСТАТ. КОЛЛАГЕН. С СЕРЕБРОМ 50Х50Х7ММ №10 /ЗЕЛЕНАЯ ДУБРАВА/ | K57: Фармкомплект ООО | L57: ЗЕЛЕНАЯ ДУБРАВА | M57: 1 | N57: 64.71 | O57: 102 | P57: 10 | Q57: 9 | R57: 200010000065 | S57: 29 | T57: 1 | U57: 2 | V57: =O57*M57 -> 102
A58: 44774 | B58: 0.43896991 | C58: 1290 | D58: 13002561 | E58: 13 | F58: 22589 | G58: Розничная реализация | H58: 15 | I58: 168795 | J58: СТАТИН 1Г. №5 ПОР. ПАК. (Д/ОСТАНОВКИ КРОВОТЕЧЕНИЙ) | K58: Катрен г.Химки | L58: Пальма ООО | M58: 1 | N58: 73.77 | O58: 122 | P58: 12 | Q58: 9 | R58: 200010000065 | S58: 29 | T58: 1 | U58: 7 | V58: =O58*M58 -> 122
A59: 44774 | B59: 0.43967593 | C59: 1291 | D59: 13002561 | E59: 13 | F59: 22589 | G59: Розничная реализация | H59: 15 | I59: 269 | J59: ВАЛОКОРДИН 20МЛ. КАПЛИ Д/ПРИЕМА ВНУТРЬ ФЛ./КАП. | K59: ГРАНД КАПИТАЛ СМОЛЕНСК ООО ФК | L59: КРЕВЕЛЬ МОЙЗЕЛЬБАХ ГМБХ (KREWEL ) | M59: 1 | N59: 155.68 | O59: 195 | P59: 13 | Q59: 9 | R59: 200010004067 | S59: 29 | T59: 1 | U59: 2 | V59: =O59*M59 -> 195
A60: 44774 | B60: 0.43967593 | C60: 1291 | D60: 13002561 | E60: 13 | F60: 22589 | G60: Розничная реализация | H60: 15 | I60: 2289 | J60: L-ТИРОКСИН 100МКГ. №100 ТАБ. /БЕРЛИН ХЕМИ/ | K60: Магнит Фарма ООО | L60: Берлин-Хеми АГ/Менарини Групп (Menarini ) | M60: 1 | N60: 129.03 | O60: 153 | P60: 7 | Q60: 9 | R60: 200010004067 | S60: 29 | T60: 1 | U60: 1 | V60: =O60*M60 -> 153
A61: 44774 | B61: 0.44123843 | C61: 1292 | D61: 13002561 | E61: 13 | F61: 22589 | G61: Розничная реализация | H61: 18 | I61: 41348 | J61: КЕТОНАЛ 50МГ/МЛ. 2МЛ. №10 Р-Р Д/В/В,В/М АМП. /ЛЕК/ | K61: ГРАНД КАПИТАЛ СМОЛЕНСК ООО ФК | L61: Лек Д.Д. (LEK D.D. ) | M61: 1 | N61: 205.78 | O61: 247 | P61: 12 | Q61: 9 | R61: 200010020276 | S61: 29 | T61: 1 | U61: 2 | V61: =O61*M61 -> 247
A62: 44774 | B62: 0.44123843 | C62: 1292 | D62: 13002561 | E62: 13 | F62: 22589 | G62: Розничная реализация | H62: 18 | I62: 304 | J62: ВОЛЬТАРЕН 25МГ/МЛ. 3МЛ. №5 Р-Р Д/В/М АМП. /НОВАРТИС/ГЛАКСО/ | K62: ГРАНД КАПИТАЛ СМОЛЕНСК ООО ФК | L62: ЛЕК ФАРМАСЬЮТИКАЛЗ Д.Д. | M62: 1 | N62: 104.35 | O62: 125 | P62: 6 | Q62: 9 | R62: 200010020276 | S62: 29 | T62: 1 | U62: 1 | V62: =O62*M62 -> 125
A63: 44774 | B63: 0.44123843 | C63: 1292 | D63: 13002561 | E63: 13 | F63: 22589 | G63: Розничная реализация | H63: 18 | I63: 443170 | J63: ПАСКАЛЬ ШПРИЦ 3-Х КОМП. 3МЛ. С ИГЛОЙ 22G 0,7Х40ММ. №10 [PASCAL] | K63: Катрен г.Химки | L63: ПАСКАЛЬ МЕДИКАЛ | M63: 2 | N63: 57.11 | O63: 90 | P63: 18 | Q63: 9 | R63: 200010020276 | S63: 29 | T63: 1 | U63: 4 | V63: =O63*M63 -> 180
A64: 44774 | B64: 0.44200231 | C64: 1293 | D64: 13002561 | E64: 13 | F64: 22589 | G64: Розничная реализация | H64: 18 | I64: 19646 | J64: ШИПОВНИКА ПЛОДЫ 2Г. №20 ПАК. /КРАСНОГОРСК/ | K64: Здравсервис | L64: КРАСНОГОРСКЛЕКСРЕДСТВА ОАО | M64: 1 | N64: 88.91 | O64: 127 | P64: 0 | Q64: NULL | R64: NULL | S64: 29 | T64: 1 | U64: 1 | V64: =O64*M64 -> 127
A65: 44774 | B65: 0.44326389 | C65: 1294 | D65: 13002561 | E65: 13 | F65: 22589 | G65: Розничная реализация | H65: 18 | I65: 105888 | J65: АСЕПТИКА САЛФЕТКА СПИРТОВАЯ 60Х100 №20 | K65: Здравсервис | L65: АСЕПТИКА ООО | M65: 1 | N65: 35.77 | O65: 58 | P65: 0 | Q65: NULL | R65: NULL | S65: 29 | T65: 1 | U65: 1 | V65: =O65*M65 -> 58
A66: 44774 | B66: 0.57680556 | C66: 1348 | D66: 13002561 | E66: 13 | F66: 22589 | G66: Розничная реализация | H66: 15 | I66: 105888 | J66: АСЕПТИКА САЛФЕТКА СПИРТОВАЯ 60Х100 №20 | K66: Здравсервис | L66: АСЕПТИКА ООО | M66: 1 | N66: 35.77 | O66: 58 | P66: 5 | Q66: 9 | R66: 200010021953 | S66: 29 | T66: 1 | U66: 1 | V66: =O66*M66 -> 58
A67: 44774 | B67: 0.44326389 | C67: 1294 | D67: 13002561 | E67: 13 | F67: 22589 | G67: Розничная реализация | H67: 18 | I67: 345578 | J67: ПАРАЦЕТАМОЛ 500МГ. №20 ТАБ. /ФАРМСТАНДАРТ/ | K67: Катрен г.Химки | L67: ФАРМСТАНДАРТ ЛЕКСРЕДСТВА ОАО | M67: 1 | N67: 20.61 | O67: 25 | P67: 0 | Q67: NULL | R67: NULL | S67: 29 | T67: 1 | U67: 2 | V67: =O67*M67 -> 25
A68: 44774 | B68: 0.79040509 | C68: 1405 | D68: 13002561 | E68: 13 | F68: 22589 | G68: Розничная реализация | H68: 18 | I68: 345578 | J68: ПАРАЦЕТАМОЛ 500МГ. №20 ТАБ. /ФАРМСТАНДАРТ/ | K68: Катрен г.Химки | L68: ФАРМСТАНДАРТ ЛЕКСРЕДСТВА ОАО | M68: 1 | N68: 20.61 | O68: 25 | P68: 0 | Q68: NULL | R68: NULL | S68: 29 | T68: 1 | U68: 7 | V68: =O68*M68 -> 25
A69: 44774 | B69: 0.44326389 | C69: 1294 | D69: 13002561 | E69: 13 | F69: 22589 | G69: Розничная реализация | H69: 18 | I69: 338912 | J69: ЦИАНОКОБАЛАМИН 0,5МГ/МЛ. 1МЛ. №10 Р-Р Д/ИН. АМП. (ВИТАМИН В12) /ДАЛЬХИМФАРМ/ | K69: ВИТТА КОМПАНИ ООО | L69: Дальхимфарм ОАО | M69: 1 | N69: 37.95 | O69: 47.04 | P69: 0 | Q69: NULL | R69: NULL | S69: 29 | T69: 1 | U69: 4 | V69: =O69*M69 -> 47.04
A70: 44774 | B70: 0.44415509 | C70: 1295 | D70: 13002561 | E70: 13 | F70: 22589 | G70: Розничная реализация | H70: 15 | I70: 157466 | J70: Д.ТАЙСС АНГИ СЕПТ ЛИМОН №24 ТАБ. Д/РАСС. | K70: ГРАНД КАПИТАЛ СМОЛЕНСК ООО ФК | L70: Др. Тайсс Натурварен ГмбХ (THEISS ) | M70: 1 | N70: 169.99 | O70: 233 | P70: 16 | Q70: 9 | R70: 200010013040 | S70: 29 | T70: 1 | U70: 1 | V70: =O70*M70 -> 233
A71: 44774 | B71: 0.44601852 | C71: 1296 | D71: 13002561 | E71: 13 | F71: 22589 | G71: Розничная реализация | H71: 15 | I71: 74670 | J71: ПРОПОСОЛ 25Г. СПРЕЙ Д/МЕСТ.ПРИМ. БАЛЛОН /АЛТАЙВИТАМИНЫ/ | K71: ООО "Акцентмед" | L71: АЛТАЙВИТАМИНЫ | M71: 1 | N71: 93.55 | O71: 133 | P71: 9 | Q71: 9 | R71: 200010007414 | S71: 29 | T71: 1 | U71: 4 | V71: =O71*M71 -> 133
A72: 44774 | B72: 0.44601852 | C72: 1296 | D72: 13002561 | E72: 13 | F72: 22589 | G72: Розничная реализация | H72: 15 | I72: 468466 | J72: ИНГАВИРИН 90МГ. №10 КАПС. /ВАЛЕНТА/ | K72: Катрен г.Химки | L72: ВАЛЕНТА ФАРМ | M72: 1 | N72: 666.45 | O72: 739 | P72: 22 | Q72: 9 | R72: 200010007414 | S72: 29 | T72: 1 | U72: 2 | V72: =O72*M72 -> 739
A73: 44774 | B73: 0.44601852 | C73: 1296 | D73: 13002561 | E73: 13 | F73: 22589 | G73: Розничная реализация | H73: 15 | I73: 167293 | J73: ДОРИТРИЦИН №10 ТАБ. Д/РАСС. | K73: Пульс | L73: МЕДИЦЕ АРЦН.ПЮТТЕР | M73: 1 | N73: 360.47 | O73: 476 | P73: 33 | Q73: 9 | R73: 200010007414 | S73: 29 | T73: 1 | U73: 1 | V73: =O73*M73 -> 476
A74: 44774 | B74: 0.44601852 | C74: 1296 | D74: 13002561 | E74: 13 | F74: 22589 | G74: Розничная реализация | H74: 15 | I74: 954 | J74: ПИНОСОЛ 10МЛ. НАЗАЛ.КАПЛИ ФЛ./КАП. | K74: Фармкомплект ООО | L74: САНЕКА ФАРМАСЬЮТИКАЛС А.С. (SANECA ) | M74: 1 | N74: 206.7 | O74: 280 | P74: 19 | Q74: 9 | R74: 200010007414 | S74: 29 | T74: 1 | U74: 3 | V74: =O74*M74 -> 280
A75: 44774 | B75: 0.44861111 | C75: 1297 | D75: 13002561 | E75: 13 | F75: 22589 | G75: Розничная реализация | H75: 15 | I75: 8529 | J75: РИНОФЛУИМУЦИЛ 10МЛ. СПРЕЙ НАЗАЛ. ФЛ. /ЗАМБОН/ | K75: Пульс | L75: ZAMBON GROUP (ЗАМБОН ) | M75: 1 | N75: 299.66 | O75: 405 | P75: 0 | Q75: NULL | R75: NULL | S75: 29 | T75: 1 | U75: 5 | V75: =O75*M75 -> 405
A76: 44774 | B76: 0.44861111 | C76: 1297 | D76: 13002561 | E76: 13 | F76: 22589 | G76: Розничная реализация | H76: 15 | I76: 4735 | J76: ЮНИДОКС СОЛЮТАБ 100МГ. №10 ТАБ.ДИСПЕРГ. /АСТЕЛЛАС/ | K76: Пульс | L76: ЗиО ЗДОРОВЬЕ ЗАО | M76: 1 | N76: 311.78 | O76: 370 | P76: 0 | Q76: NULL | R76: NULL | S76: 29 | T76: 1 | U76: 6 | V76: =O76*M76 -> 370
A77: 44774 | B77: 0.44861111 | C77: 1297 | D77: 13002561 | E77: 13 | F77: 22589 | G77: Розничная реализация | H77: 15 | I77: 512333 | J77: ДЕЗЛОРАТАДИН-ВЕЛФАРМ 5МГ. №10 ТАБ. П/О | K77: ВИТТА КОМПАНИ ООО | L77: ВЕЛФАРМ ООО | M77: 1 | N77: 115.28 | O77: 158 | P77: 0 | Q77: NULL | R77: NULL | S77: 29 | T77: 1 | U77: 1 | V77: =O77*M77 -> 158
A78: 44774 | B78: 0.44861111 | C78: 1297 | D78: 13002561 | E78: 13 | F78: 22589 | G78: Розничная реализация | H78: 15 | I78: 292820 | J78: КАЛИНОВ РОДНИК ВОДА МИНЕР. 0,5Л. Н/ГАЗ. | K78: ПрофитМед | L78: ФОНТЕ-АКВА | M78: 1 | N78: 23.04 | O78: 38 | P78: 0 | Q78: NULL | R78: NULL | S78: 29 | T78: 1 | U78: 2 | V78: =O78*M78 -> 38
A79: 44774 | B79: 0.44861111 | C79: 1297 | D79: 13002561 | E79: 13 | F79: 22589 | G79: Розничная реализация | H79: 15 | I79: 1504331 | J79: Карта LOYALITY 0,01Р | K79: ООО "Континент" | L79: ФОНТЕ-АКВА | M79: 1 | N79: 0.01 | O79: 0.01 | P79: 0 | Q79: NULL | R79: NULL | S79: 29 | T79: 1 | U79: 3 | V79: =O79*M79 -> 0.01
A80: 44774 | B80: 0.48900463 | C80: 1312 | D80: 13002561 | E80: 13 | F80: 22589 | G80: Розничная реализация | H80: 18 | I80: 1504331 | J80: Карта LOYALITY 0,01Р | K80: ООО "Континент" | L80: ФОНТЕ-АКВА | M80: 1 | N80: 0.01 | O80: 0.01 | P80: 0 | Q80: NULL | R80: NULL | S80: 29 | T80: 1 | U80: 2 | V80: =O80*M80 -> 0.01
A81: 44774 | B81: 0.74574074 | C81: 1394 | D81: 13002561 | E81: 13 | F81: 22589 | G81: Розничная реализация | H81: 18 | I81: 1504331 | J81: Карта LOYALITY 0,01Р | K81: ООО "Континент" | L81: ФОНТЕ-АКВА | M81: 1 | N81: 0.01 | O81: 0.01 | P81: 0 | Q81: NULL | R81: NULL | S81: 29 | T81: 1 | U81: 1 | V81: =O81*M81 -> 0.01
A82: 44774 | B82: 0.45111111 | C82: 1298 | D82: 13002561 | E82: 13 | F82: 22589 | G82: Розничная реализация | H82: 18 | I82: 54354 | J82: АУГМЕНТИН 200МГ.+28,5МГ/5МЛ. 7,7Г. 70МЛ. ПОР. Д/СУСП. Д/ПРИЕМА ВНУТРЬ ФЛ. /ГЛАКСО/ | K82: Протек | L82: Глаксо Вэллком Продакшен | M82: 1 | N82: 134.66 | O82: 160 | P82: 0 | Q82: NULL | R82: NULL | S82: 29 | T82: 1 | U82: 1 | V82: =O82*M82 -> 160
A83: 44774 | B83: 0.45111111 | C83: 1298 | D83: 13002561 | E83: 13 | F83: 22589 | G83: Розничная реализация | H83: 18 | I83: 100086 | J83: ГЕКСОРАЛ ТАБС №20 ТАБ. Д/РАСС. | K83: Катрен г.Химки | L83: Зольдан Холдинг | M83: 1 | N83: 198.75 | O83: 249 | P83: 0 | Q83: NULL | R83: NULL | S83: 29 | T83: 1 | U83: 2 | V83: =O83*M83 -> 249
A84: 44774 | B84: 0.45111111 | C84: 1298 | D84: 13002561 | E84: 13 | F84: 22589 | G84: Розничная реализация | H84: 18 | I84: 46046 | J84: РОМАШКИ ЦВЕТКИ 1,5Г. №20 ПАК. /КРАСНОГОРСК/ | K84: Авеста | L84: КРАСНОГОРСКЛЕКСРЕДСТВА ОАО | M84: 1 | N84: 71.85 | O84: 103 | P84: 0 | Q84: NULL | R84: NULL | S84: 29 | T84: 1 | U84: 5 | V84: =O84*M84 -> 103
A85: 44774 | B85: 0.57680556 | C85: 1348 | D85: 13002561 | E85: 13 | F85: 22589 | G85: Розничная реализация | H85: 15 | I85: 46046 | J85: РОМАШКИ ЦВЕТКИ 1,5Г. №20 ПАК. /КРАСНОГОРСК/ | K85: Авеста | L85: КРАСНОГОРСКЛЕКСРЕДСТВА ОАО | M85: 1 | N85: 71.85 | O85: 103 | P85: 7 | Q85: 9 | R85: 200010021953 | S85: 29 | T85: 1 | U85: 6 | V85: =O85*M85 -> 103
A86: 44774 | B86: 0.45111111 | C86: 1298 | D86: 13002561 | E86: 13 | F86: 22589 | G86: Розничная реализация | H86: 18 | I86: 41241 | J86: НУРОФЕН 100МГ/5МЛ. 100МЛ. СУСП. КЛУБНИКА Д/ДЕТЕЙ ФЛ. /РЕКИТТ БЕНКИЗЕР/ | K86: Протек | L86: RECKITT BENCKISER S.A. | M86: 1 | N86: 99.97 | O86: 121.72 | P86: 0 | Q86: NULL | R86: NULL | S86: 29 | T86: 2 | U86: 3 | V86: =O86*M86 -> 121.72
A87: 44774 | B87: 0.45239583 | C87: 1299 | D87: 13002561 | E87: 13 | F87: 22589 | G87: Розничная реализация | H87: 18 | I87: 16407 | J87: РАСТОРОПША №100 ТАБ. | K87: Катрен г.Химки | L87: В-МИН ООО | M87: 1 | N87: 135.54 | O87: 211 | P87: 21 | Q87: 9 | R87: 200010023919 | S87: 29 | T87: 1 | U87: 4 | V87: =O87*M87 -> 211
A88: 44774 | B88: 0.45239583 | C88: 1299 | D88: 13002561 | E88: 13 | F88: 22589 | G88: Розничная реализация | H88: 18 | I88: 26351 | J88: 911-ВЕНОЛГОН ГЕЛЬ Д/НОГ ПРИ ТЯЖЕСТИ,БОЛИ,ОТЕКАХ 100МЛ. ТУБА | K88: Протек | L88: ТВИНС ТЭК | M88: 1 | N88: 75.81 | O88: 120 | P88: 12 | Q88: 9 | R88: 200010023919 | S88: 29 | T88: 1 | U88: 1 | V88: =O88*M88 -> 120
A89: 44774 | B89: 0.45239583 | C89: 1299 | D89: 13002561 | E89: 13 | F89: 22589 | G89: Розничная реализация | H89: 18 | I89: 22533 | J89: КОНКОР КОР 2,5МГ. №30 ТАБ. П/П/О /МЕРК/ | K89: ГРАНД КАПИТАЛ СМОЛЕНСК ООО ФК | L89: НАНОЛЕК | M89: 1 | N89: 130.83 | O89: 151 | P89: 7 | Q89: 9 | R89: 200010023919 | S89: 29 | T89: 1 | U89: 3 | V89: =O89*M89 -> 151
A90: 44774 | B90: 0.66700231 | C90: 1370 | D90: 13002561 | E90: 13 | F90: 22589 | G90: Розничная реализация | H90: 18 | I90: 22533 | J90: КОНКОР КОР 2,5МГ. №30 ТАБ. П/П/О /МЕРК/ | K90: ГРАНД КАПИТАЛ СМОЛЕНСК ООО ФК | L90: НАНОЛЕК | M90: 1 | N90: 130.83 | O90: 151 | P90: 7 | Q90: 9 | R90: 200010016459 | S90: 29 | T90: 1 | U90: 2 | V90: =O90*M90 -> 151
A91: 44774 | B91: 0.45239583 | C91: 1299 | D91: 13002561 | E91: 13 | F91: 22589 | G91: Розничная реализация | H91: 18 | I91: 488299 | J91: БИСОПРОЛОЛ 2,5МГ. №60 ТАБ. П/О /ВЕРТЕКС/ | K91: Пульс | L91: ВЕРТЕКС | M91: 1 | N91: 156.2 | O91: 186 | P91: 9 | Q91: 9 | R91: 200010023919 | S91: 29 | T91: 1 | U91: 2 | V91: =O91*M91 -> 186
A92: 44774 | B92: 0.45282407 | C92: 1300 | D92: 13002561 | E92: 13 | F92: 22589 | G92: Розничная реализация | H92: 18 | I92: 72392 | J92: СНУП 0,1% 90МКГ/ДОЗА 15МЛ. НАЗАЛ.СПРЕЙ ФЛ. /ШТАДА/ | K92: Катрен г.Химки | L92: ХЕМОМОНТ | M92: 1 | N92: 103.5 | O92: 122 | P92: 6 | Q92: 9 | R92: 200010018337 | S92: 29 | T92: 1 | U92: 1 | V92: =O92*M92 -> 122
A93: 44774 | B93: 0.81680556 | C93: 1410 | D93: 13002561 | E93: 13 | F93: 22589 | G93: Розничная реализация | H93: 18 | I93: 72392 | J93: СНУП 0,1% 90МКГ/ДОЗА 15МЛ. НАЗАЛ.СПРЕЙ ФЛ. /ШТАДА/ | K93: Катрен г.Химки | L93: ХЕМОМОНТ | M93: 1 | N93: 103.5 | O93: 122 | P93: 6 | Q93: 9 | R93: 200010015192 | S93: 29 | T93: 1 | U93: 2 | V93: =O93*M93 -> 122
A94: 44774 | B94: 0.46287037 | C94: 1301 | D94: 13002561 | E94: 13 | F94: 22589 | G94: Розничная реализация | H94: 18 | I94: 17182 | J94: ПОЛИДЕКСА С ФЕНИЛЭФРИНОМ 15МЛ. НАЗАЛ.СПРЕЙ ФЛ. | K94: Здравсервис | L94: LABORATORIES DU DOCTEUR EMILE BOUCHARA | M94: 1 | N94: 525 | O94: 678 | P94: 20.21 | Q94: 925 | R94: 200000000492 | S94: 29 | T94: 1 | U94: 1 | V94: =O94*M94 -> 678
A95: 44774 | B95: 0.46287037 | C95: 1301 | D95: 13002561 | E95: 13 | F95: 22589 | G95: Розничная реализация | H95: 18 | I95: 26900 | J95: РЕГЕЦИН 15Г. ГЕЛЬ П/УГРЕВОЙ СЫПИ | K95: Здравсервис | L95: ДИОНИС ООО | M95: 1 | N95: 190 | O95: 295 | P95: 8.79 | Q95: 925 | R95: 200000000492 | S95: 29 | T95: 1 | U95: 2 | V95: =O95*M95 -> 295
A96: 44774 | B96: 0.46440972 | C96: 1302 | D96: 13002561 | E96: 13 | F96: 22589 | G96: Розничная реализация | H96: 15 | I96: 30028 | J96: ГЕМАТОГЕН РУССКИЙ ДЕТСКИЙ 40Г. ПЛИТКА /ФАРМ-ПРО/ | K96: Катрен г.Химки | L96: ФАРМ-ПРО | M96: 2 | N96: 10.01 | O96: 17 | P96: 3 | Q96: 9 | R96: 200010019633 | S96: 29 | T96: 1 | U96: 1 | V96: =O96*M96 -> 34
A97: 44774 | B97: 0.60392361 | C97: 1356 | D97: 13002561 | E97: 13 | F97: 22589 | G97: Розничная реализация | H97: 18 | I97: 30028 | J97: ГЕМАТОГЕН РУССКИЙ ДЕТСКИЙ 40Г. ПЛИТКА /ФАРМ-ПРО/ | K97: Катрен г.Химки | L97: ФАРМ-ПРО | M97: 1 | N97: 10.01 | O97: 17 | P97: 0 | Q97: NULL | R97: NULL | S97: 29 | T97: 1 | U97: 1 | V97: =O97*M97 -> 17
A98: 44774 | B98: 0.46513889 | C98: 1303 | D98: 13002561 | E98: 13 | F98: 22589 | G98: Розничная реализация | H98: 15 | I98: 371526 | J98: ТИАМИНА ХЛОРИД 50МГ/МЛ. 1МЛ. №10 Р-Р Д/В/М ВВЕД. АМП. (ВИТАМИН В1) /СТАТУСФАРМ/ЕРЕВАН.ФФ/ | K98: Пульс | L98: СТАТУСФАРМ ООО | M98: 1 | N98: 27.12 | O98: 33 | P98: 1 | Q98: 9 | R98: 200010000167 | S98: 29 | T98: 1 | U98: 1 | V98: =O98*M98 -> 33
A99: 44774 | B99: 0.46513889 | C99: 1303 | D99: 13002561 | E99: 13 | F99: 22589 | G99: Розничная реализация | H99: 15 | I99: 371526 | J99: ТИАМИНА ХЛОРИД 50МГ/МЛ. 1МЛ. №10 Р-Р Д/В/М ВВЕД. АМП. (ВИТАМИН В1) /СТАТУСФАРМ/ЕРЕВАН.ФФ/ | K99: ВИТТА КОМПАНИ ООО | L99: СТАТУСФАРМ ООО | M99: 1 | N99: 27.06 | O99: 33.54 | P99: 1.54 | Q99: 9 | R99: 200010000167 | S99: 29 | T99: 1 | U99: 2 | V99: =O99*M99 -> 33.54
A100: 44774 | B100: 0.46856481 | C100: 1304 | D100: 13002561 | E100: 13 | F100: 22589 | G100: Розничная реализация | H100: 15 | I100: 79666 | J100: АРКОКСИА 90МГ. №28 ТАБ. П/П/О | K100: Катрен г.Химки | L100: РОВИ КОНТРАКТ | M100: 1 | N100: 1380.93 | O100: 1727 | P100: 120 | Q100: 9 | R100: 200010026858 | S100: 29 | T100: 1 | U100: 1 | V100: =O100*M100 -> 1727
...

Sheet Лист11
A3: Названия строк | B3: Количество по полю ABC-XYZ
A4: AAAZ | B4: 176
A5: AABZ | B5: 6
A6: ABAZ | B6: 83
A7: ABBZ | B7: 59
A8: ACAZ | B8: 70
A9: ACBZ | B9: 29
A10: ACCZ | B10: 29
A11: BAAZ | B11: 98
A12: BABZ | B12: 5
A13: BBBZ | B13: 73
A14: BCBZ | B14: 37
A15: BCCZ | B15: 29
... A23: Общий итог | B23: 803

Sheet ABC
A1: Название | B1: Кол-во продаж | C1: доля | D1: кумулята | E1: тир | F1: Сумма продаж | G1: доля | H1: кумулята | I1: тир | J1: М. обор | K1: доля | L1: кумулята | M1: тир | N1: ABC | O1: var | P1: XYZ | Q1: ABC-XYZ
A2: ЛЕЙКОПЛАСТЫРЬ БАКТЕР. 2,5Х7,2 №1 /ВЕРОФАРМ/ | B2: 68 | C2: 0.04 | D2: 0.04 | E2: A | F2: 272 | G2: 0.00073894542 | H2: 0.8596827 | I2: B | J2: 408 | K2: =J2/SUM(J:J) -> 0.042265927 | L2: =K2 -> 0.042265927 | M2: =IF(L2<0.8,"A",IF(L2<0.95,"B","C")) -> A | N2: =E2&I2&M2 -> ABA | O2: =VLOOKUP(A2,XYZ!A1:G804,2,FALSE) -> 0.89693828 | P2: =IF(O2<0.1,"A",IF(O2<0.25,"Y","Z")) -> Z | Q2: =N2&P2 -> ABAZ
A3: НАФТИЗИН 0,1% 15МЛ. НАЗАЛ.КАПЛИ ФЛ./КАП. /СЛАВЯНСКАЯ АПТЕКА/ | B3: 35 | C3: 0.02 | D3: 0.06 | E3: A | F3: 280 | G3: 0.00076067911 | H3: 0.84995415 | I3: B | J3: 210 | K3: =J3/SUM(J:J) -> 0.021754521 | L3: =K3+L2 -> 0.064020449 | M3: =IF(L3<0.8,"A",IF(L3<0.95,"B","C")) -> A | N3: =E3&I3&M3 -> ABA | O3: =VLOOKUP(A3,XYZ!A2:G805,2,FALSE) -> 0.69985421 | P3: =IF(O3<0.1,"A",IF(O3<0.25,"Y","Z")) -> Z | Q3: =N3&P3 -> ABAZ
A4: ПАКЕТ | B4: 26 | C4: 0.02 | D4: 0.08 | E4: A | F4: 52 | G4: 0.00014126898 | H4: 0.99458992 | I4: C | J4: 156 | K4: =J4/SUM(J:J) -> 0.016160502 | L4: =K4+L3 -> 0.08018095 | M4: =IF(L4<0.8,"A",IF(L4<0.95,"B","C")) -> A | N4: =E4&I4&M4 -> ACA | O4: =VLOOKUP(A4,XYZ!A3:G806,2,FALSE) -> 0.61418152 | P4: =IF(O4<0.1,"A",IF(O4<0.25,"Y","Z")) -> Z | Q4: =N4&P4 -> ACAZ
A5: ВАЛИДОЛ 60МГ. №10 ТАБ. ПОДЪЯЗЫЧ. /ФАРМСТАНДАРТ/ | B5: 25 | C5: 0.02 | D5: 0.1 | E5: A | F5: 892 | G5: 0.0024233063 | H5: 0.46855501 | I5: A | J5: 150 | K5: =J5/SUM(J:J) -> 0.015538944 | L5: =K5+L4 -> 0.095719894 | M5: =IF(L5<0.8,"A",IF(L5<0.95,"B","C")) -> A | N5: =E5&I5&M5 -> AAA | O5: =VLOOKUP(A5,XYZ!A4:G807,2,FALSE) -> 0.70710678 | P5: =IF(O5<0.1,"A",IF(O5<0.25,"Y","Z")) -> Z | Q5: =N5&P5 -> AAAZ
A6: БОРНАЯ К-ТА 10Г. ДЕЗ.СР-ВО ПОР. (НДС 20%) | B6: 22 | C6: 0.01 | D6: 0.11 | E6: A | F6: 308 | G6: 0.00083674702 | H6: 0.823596 | I6: B | J6: 132 | K6: =J6/SUM(J:J) -> 0.013674271 | L6: =K6+L5 -> 0.10939416 | M6: =IF(L6<0.8,"A",IF(L6<0.95,"B","C")) -> A | N6: =E6&I6&M6 -> ABA | O6: =VLOOKUP(A6,XYZ!A5:G808,2,FALSE) -> 2.236068 | P6: =IF(O6<0.1,"A",IF(O6<0.25,"Y","Z")) -> Z | Q6: =N6&P6 -> ABAZ
A7: ГЕМАТОГЕН РУССКИЙ ДЕТСКИЙ 40Г. ПЛИТКА /ФАРМ-ПРО/ | B7: 17 | C7: 0.01 | D7: 0.12 | E7: A | F7: 289 | G7: 0.00078512951 | H7: 0.84067659 | I7: B | J7: 102 | K7: =J7/SUM(J:J) -> 0.010566482 | L7: =K7+L6 -> 0.11996065 | M7: =IF(L7<0.8,"A",IF(L7<0.95,"B","C")) -> A | N7: =E7&I7&M7 -> ABA | O7: =VLOOKUP(A7,XYZ!A6:G809,2,FALSE) -> 0.4460515 | P7: =IF(O7<0.1,"A",IF(O7<0.25,"Y","Z")) -> Z | Q7: =N7&P7 -> ABAZ
A8: КОРВАЛОЛ 25МЛ. КАПЛИ Д/ПРИЕМА ВНУТРЬ ФЛ. И/У /ФАРМСТАНДАРТ ЛЕКСРЕДСТВА/ | B8: 14 | C8: 0.01 | D8: 0.13 | E8: A | F8: 364 | G8: 0.00098888284 | H8: 0.78322078 | I8: A | J8: 84 | K8: =J8/SUM(J:J) -> 0.0087018086 | L8: =K8+L7 -> 0.12866246 | M8: =IF(L8<0.8,"A",IF(L8<0.95,"B","C")) -> A | N8: =E8&I8&M8 -> AAA | O8: =VLOOKUP(A8,XYZ!A7:G810,2,FALSE) -> 0.85266688 | P8: =IF(O8<0.1,"A",IF(O8<0.25,"Y","Z")) -> Z | Q8: =N8&P8 -> AAAZ
A9: ЛЕЙКОПЛАСТЫРЬ БАКТЕР. 4Х10 №1 /ВЕРОФАРМ/ | B9: 14 | C9: 0.01 | D9: 0.14 | E9: A | F9: 126 | G9: 0.0003423056 | H9: 0.9543221 | I9: C | J9: 84 | K9: =J9/SUM(J:J) -> 0.0087018086 | L9: =K9+L8 -> 0.13736426 | M9: =IF(L9<0.8,"A",IF(L9<0.95,"B","C")) -> A | N9: =E9&I9&M9 -> ACA | O9: =VLOOKUP(A9,XYZ!A8:G811,2,FALSE) -> 1.5649216 | P9: =IF(O9<0.1,"A",IF(O9<0.25,"Y","Z")) -> Z | Q9: =N9&P9 -> ACAZ
A10: РАУНАТИН 2МГ. №50 ТАБ. П/О /ЗДОРОВЬЕ/ | B10: 13 | C10: 0.01 | D10: 0.17 | E10: A | F10: 1673 | G10: 0.0045450577 | H10: 0.24991442 | I10: A | J10: 78 | K10: =J10/SUM(J:J) -> 0.0080802508 | L10: =K10+L9 -> 0.14544451 | M10: =IF(L10<0.8,"A",IF(L10<0.95,"B","C")) -> A | N10: =E10&I10&M10 -> AAA | O10: =VLOOKUP(A10,XYZ!A9:G812,2,FALSE) -> 2.236068 | P10: =IF(O10<0.1,"A",IF(O10<0.25,"Y","Z")) -> Z | Q10: =N10&P10 -> AAAZ
A11: МЕНОВАЗИН 40МЛ. №1 СПИРТ. Р-Р Д/НАРУЖ.ПРИМ. ФЛ. /САМАРАМЕДПРОМ/ | B11: 13 | C11: 0.01 | D11: 0.15 | E11: A | F11: 468 | G11: 0.0012714208 | H11: 0.6943465 | I11: A | J11: 78 | K11: =J11/SUM(J:J) -> 0.0080802508 | L11: =K11+L10 -> 0.15352477 | M11: =IF(L11<0.8,"A",IF(L11<0.95,"B","C")) -> A | N11: =E11&I11&M11 -> AAA | O11: =VLOOKUP(A11,XYZ!A10:G813,2,FALSE) -> 1.0029542 | P11: =IF(O11<0.1,"A",IF(O11<0.25,"Y","Z")) -> Z | Q11: =N11&P11 -> AAAZ
A12: ПЕРЕКИСЬ ВОДОРОДА 3% 100МЛ. №1 Р-Р ДЕЗ.СР-ВО ФЛ. (НДС 20%) | B12: 13 | C12: 0.01 | D12: 0.16 | E12: A | F12: 221 | G12: 0.00060039316 | H12: 0.89687121 | I12: B | J12: 78 | K12: =J12/SUM(J:J) -> 0.0080802508 | L12: =K12+L11 -> 0.16160502 | M12: =IF(L12<0.8,"A",IF(L12<0.95,"B","C")) -> A | N12: =E12&I12&M12 -> ABA | O12: =VLOOKUP(A12,XYZ!A11:G814,2,FALSE) -> 0.88545111 | P12: =IF(O12<0.1,"A",IF(O12<0.25,"Y","Z")) -> Z | Q12: =N12&P12 -> ABAZ
A13: ЛЕЙКОПЛАСТЫРЬ БАКТЕР. 6X10 №1 /ВЕРОФАРМ/ | B13: 13 | C13: 0.01 | D13: 0.15 | E13: A | F13: 104 | G13: 0.00028253796 | H13: 0.96752165 | I13: C | J13: 78 | K13: =J13/SUM(J:J) -> 0.0080802508 | L13: =K13+L12 -> 0.16968527 | M13: =IF(L13<0.8,"A",IF(L13<0.95,"B","C")) -> A | N13: =E13&I13&M13 -> ACA | O13: =VLOOKUP(A13,XYZ!A12:G815,2,FALSE) -> 1.6676526 | P13: =IF(O13<0.1,"A",IF(O13<0.25,"Y","Z")) -> Z | Q13: =N13&P13 -> ACAZ
A14: Карта LOYALITY 0,01Р | B14: 12 | C14: 0.01 | D14: 0.18 | E14: A | F14: 0.12 | G14: 3.2600533e-07 | H14: 1 | I14: C | J14: 72 | K14: =J14/SUM(J:J) -> 0.007458693 | L14: =K14+L13 -> 0.17714396 | M14: =IF(L14<0.8,"A",IF(L14<0.95,"B","C")) -> A | N14: =E14&I14&M14 -> ACA | O14: =VLOOKUP(A14,XYZ!A13:G816,2,FALSE) -> 0.372678 | P14: =IF(O14<0.1,"A",IF(O14<0.25,"Y","Z")) -> Z | Q14: =N14&P14 -> ACAZ
... A804: ХАРТМАНН КОСМОПОР Е ПОВЯЗКА 7,2Х5СМ №50 П/ОПЕР. САМОКЛ. СТЕР. /АРТ.9008705/ [HARTMANN COSMOPOR] | B804: 0.04 | C804: 0 | D804: 1 | E804: C | F804: 25.8 | G804: 7.0091147e-05 | H804: 0.99952697 | I804: C | J804: 0.24 | K804: =J804/SUM(J:J) -> 2.486231e-05 | L804: =K804+L803 -> 1 | M804: =IF(L804<0.8,"A",IF(L804<0.95,"B","C")) -> C | N804: =E804&I804&M804 -> CCC | O804: =VLOOKUP(A804,XYZ!A803:G1606,2,FALSE) -> 2.236068 | P804: =IF(O804<0.1,"A",IF(O804<0.25,"Y","Z")) -> Z | Q804: =N804&P804 -> CCCZ

Sheet XYZ
A1: Название | B1: VAR | C1: 44774 | D1: 44775 | E1: 44776 | F1: 44777 | G1: 44778
A2: ЛЕЙКОПЛАСТЫРЬ БАКТЕР. 2,5Х7,2 №1 /ВЕРОФАРМ/ | B2: =_xlfn.STDEV.S(C2:G2)/AVERAGE(C2:G2) -> 0.89693828 | C2: =SUMIFS('data (1)'!$M:$M,'data (1)'!$A:$A,XYZ!C$1,'data (1)'!$J:$J,XYZ!$A2) -> 24 | D2: =SUMIFS('data (1)'!$M:$M,'data (1)'!$A:$A,XYZ!D$1,'data (1)'!$J:$J,XYZ!$A2) -> 0 | E2: =SUMIFS('data (1)'!$M:$M,'data (1)'!$A:$A,XYZ!E$1,'data (1)'!$J:$J,XYZ!$A2) -> 4 | F2: =SUMIFS('data (1)'!$M:$M,'data (1)'!$A:$A,XYZ!F$1,'data (1)'!$J:$J,XYZ!$A2) -> 12 | G2: =SUMIFS('data (1)'!$M:$M,'data (1)'!$A:$A,XYZ!G$1,'data (1)'!$J:$J,XYZ!$A2) -> 28
A3: НАФТИЗИН 0,1% 15МЛ. НАЗАЛ.КАПЛИ ФЛ./КАП. /СЛАВЯНСКАЯ АПТЕКА/ | B3: =_xlfn.STDEV.S(C3:G3)/AVERAGE(C3:G3) -> 0.69985421 | C3: =SUMIFS('data (1)'!$M:$M,'data (1)'!$A:$A,XYZ!C$1,'data (1)'!$J:$J,XYZ!$A3) -> 2 | D3: =SUMIFS('data (1)'!$M:$M,'data (1)'!$A:$A,XYZ!D$1,'data (1)'!$J:$J,XYZ!$A3) -> 10 | E3: =SUMIFS('data (1)'!$M:$M,'data (1)'!$A:$A,XYZ!E$1,'data (1)'!$J:$J,XYZ!$A3) -> 5 | F3: =SUMIFS('data (1)'!$M:$M,'data (1)'!$A:$A,XYZ!F$1,'data (1)'!$J:$J,XYZ!$A3) -> 4 | G3: =SUMIFS('data (1)'!$M:$M,'data (1)'!$A:$A,XYZ!G$1,'data (1)'!$J:$J,XYZ!$A3) -> 14
A4: ПАКЕТ | B4: =_xlfn.STDEV.S(C4:G4)/AVERAGE(C4:G4) -> 0.61418152 | C4: =SUMIFS('data (1)'!$M:$M,'data (1)'!$A:$A,XYZ!C$1,'data (1)'!$J:$J,XYZ!$A4) -> 10 | D4: =SUMIFS('data (1)'!$M:$M,'data (1)'!$A:$A,XYZ!D$1,'data (1)'!$J:$J,XYZ!$A4) -> 3 | E4: =SUMIFS('data (1)'!$M:$M,'data (1)'!$A:$A,XYZ!E$1,'data (1)'!$J:$J,XYZ!$A4) -> 3 | F4: =SUMIFS('data (1)'!$M:$M,'data (1)'!$A:$A,XYZ!F$1,'data (1)'!$J:$J,XYZ!$A4) -> 3 | G4: =SUMIFS('data (1)'!$M:$M,'data (1)'!$A:$A,XYZ!G$1,'data (1)'!$J:$J,XYZ!$A4) -> 7
A5: ВАЛИДОЛ 60МГ. №10 ТАБ. ПОДЪЯЗЫЧ. /ФАРМСТАНДАРТ/ | B5: =_xlfn.STDEV.S(C5:G5)/AVERAGE(C5:G5) -> 0.70710678 | C5: =SUMIFS('data (1)'!$M:$M,'data (1)'!$A:$A,XYZ!C$1,'data (1)'!$J:$J,XYZ!$A5) -> 2 | D5: =SUMIFS('data (1)'!$M:$M,'data (1)'!$A:$A,XYZ!D$1,'data (1)'!$J:$J,XYZ!$A5) -> 5 | E5: =SUMIFS('data (1)'!$M:$M,'data (1)'!$A:$A,XYZ!E$1,'data (1)'!$J:$J,XYZ!$A5) -> 4 | F5: =SUMIFS('data (1)'!$M:$M,'data (1)'!$A:$A,XYZ!F$1,'data (1)'!$J:$J,XYZ!$A5) -> 11 | G5: =SUMIFS('data (1)'!$M:$M,'data (1)'!$A:$A,XYZ!G$1,'data (1)'!$J:$J,XYZ!$A5) -> 3
A6: БОРНАЯ К-ТА 10Г. ДЕЗ.СР-ВО ПОР. (НДС 20%) | B6: =_xlfn.STDEV.S(C6:G6)/AVERAGE(C6:G6) -> 2.236068 | C6: =SUMIFS('data (1)'!$M:$M,'data (1)'!$A:$A,XYZ!C$1,'data (1)'!$J:$J,XYZ!$A6) -> 0 | D6: =SUMIFS('data (1)'!$M:$M,'data (1)'!$A:$A,XYZ!D$1,'data (1)'!$J:$J,XYZ!$A6) -> 22 | E6: =SUMIFS('data (1)'!$M:$M,'data (1)'!$A:$A,XYZ!E$1,'data (1)'!$J:$J,XYZ!$A6) -> 0 | F6: =SUMIFS('data (1)'!$M:$M,'data (1)'!$A:$A,XYZ!F$1,'data (1)'!$J:$J,XYZ!$A6) -> 0 | G6: =SUMIFS('data (1)'!$M:$M,'data (1)'!$A:$A,XYZ!G$1,'data (1)'!$J:$J,XYZ!$A6) -> 0
A7: ГЕМАТОГЕН РУССКИЙ ДЕТСКИЙ 40Г. ПЛИТКА /ФАРМ-ПРО/ | B7: =_xlfn.STDEV.S(C7:G7)/AVERAGE(C7:G7) -> 0.4460515 | C7: =SUMIFS('data (1)'!$M:$M,'data (1)'!$A:$A,XYZ!C$1,'data (1)'!$J:$J,XYZ!$A7) -> 3 | D7: =SUMIFS('data (1)'!$M:$M,'data (1)'!$A:$A,XYZ!D$1,'data (1)'!$J:$J,XYZ!$A7) -> 3 | E7: =SUMIFS('data (1)'!$M:$M,'data (1)'!$A:$A,XYZ!E$1,'data (1)'!$J:$J,XYZ!$A7) -> 6 | F7: =SUMIFS('data (1)'!$M:$M,'data (1)'!$A:$A,XYZ!F$1,'data (1)'!$J:$J,XYZ!$A7) -> 3 | G7: =SUMIFS('data (1)'!$M:$M,'data (1)'!$A:$A,XYZ!G$1,'data (1)'!$J:$J,XYZ!$A7) -> 2
A8: КОРВАЛОЛ 25МЛ. КАПЛИ Д/ПРИЕМА ВНУТРЬ ФЛ. И/У /ФАРМСТАНДАРТ ЛЕКСРЕДСТВА/ | B8: =_xlfn.STDEV.S(C8:G8)/AVERAGE(C8:G8) -> 0.85266688 | C8: =SUMIFS('data (1)'!$M:$M,'data (1)'!$A:$A,XYZ!C$1,'data (1)'!$J:$J,XYZ!$A8) -> 4 | D8: =SUMIFS('data (1)'!$M:$M,'data (1)'!$A:$A,XYZ!D$1,'data (1)'!$J:$J,XYZ!$A8) -> 0 | E8: =SUMIFS('data (1)'!$M:$M,'data (1)'!$A:$A,XYZ!E$1,'data (1)'!$J:$J,XYZ!$A8) -> 6 | F8: =SUMIFS('data (1)'!$M:$M,'data (1)'!$A:$A,XYZ!F$1,'data (1)'!$J:$J,XYZ!$A8) -> 3 | G8: =SUMIFS('data (1)'!$M:$M,'data (1)'!$A:$A,XYZ!G$1,'data (1)'!$J:$J,XYZ!$A8) -> 1
A9: ЛЕЙКОПЛАСТЫРЬ БАКТЕР. 4Х10 №1 /ВЕРОФАРМ/ | B9: =_xlfn.STDEV.S(C9:G9)/AVERAGE(C9:G9) -> 1.5649216 | C9: =SUMIFS('data (1)'!$M:$M,'data (1)'!$A:$A,XYZ!C$1,'data (1)'!$J:$J,XYZ!$A9) -> 0 | D9: =SUMIFS('data (1)'!$M:$M,'data (1)'!$A:$A,XYZ!D$1,'data (1)'!$J:$J,XYZ!$A9) -> 0 | E9: =SUMIFS('data (1)'!$M:$M,'data (1)'!$A:$A,XYZ!E$1,'data (1)'!$J:$J,XYZ!$A9) -> 0 | F9: =SUMIFS('data (1)'!$M:$M,'data (1)'!$A:$A,XYZ!F$1,'data (1)'!$J:$J,XYZ!$A9) -> 10 | G9: =SUMIFS('data (1)'!$M:$M,'data (1)'!$A:$A,XYZ!G$1,'data (1)'!$J:$J,XYZ!$A9) -> 4
A10: РАУНАТИН 2МГ. №50 ТАБ. П/О /ЗДОРОВЬЕ/ | B10: =_xlfn.STDEV.S(C10:G10)/AVERAGE(C10:G10) -> 2.236068 | C10: =SUMIFS('data (1)'!$M:$M,'data (1)'!$A:$A,XYZ!C$1,'data (1)'!$J:$J,XYZ!$A10) -> 0 | D10: =SUMIFS('data (1)'!$M:$M,'data (1)'!$A:$A,XYZ!D$1,'data (1)'!$J:$J,XYZ!$A10) -> 0 | E10: =SUMIFS('data (1)'!$M:$M,'data (1)'!$A:$A,XYZ!E$1,'data (1)'!$J:$J,XYZ!$A10) -> 0 | F10: =SUMIFS('data (1)'!$M:$M,'data (1)'!$A:$A,XYZ!F$1,'data (1)'!$J:$J,XYZ!$A10) -> 0 | G10: =SUMIFS('data (1)'!$M:$M,'data (1)'!$A:$A,XYZ!G$1,'data (1)'!$J:$J,XYZ!$A10) -> 13
A11: МЕНОВАЗИН 40МЛ. №1 СПИРТ. Р-Р Д/НАРУЖ.ПРИМ. ФЛ. /САМАРАМЕДПРОМ/ | B11: =_xlfn.STDEV.S(C11:G11)/AVERAGE(C11:G11) -> 1.0029542 | C11: =SUMIFS('data (1)'!$M:$M,'data (1)'!$A:$A,XYZ!C$1,'data (1)'!$J:$J,XYZ!$A11) -> 4 | D11: =SUMIFS('data (1)'!$M:$M,'data (1)'!$A:$A,XYZ!D$1,'data (1)'!$J:$J,XYZ!$A11) -> 6 | E11: =SUMIFS('data (1)'!$M:$M,'data (1)'!$A:$A,XYZ!E$1,'data (1)'!$J:$J,XYZ!$A11) -> 3 | F11: =SUMIFS('data (1)'!$M:$M,'data (1)'!$A:$A,XYZ!F$1,'data (1)'!$J:$J,XYZ!$A11) -> 0 | G11: =SUMIFS('data (1)'!$M:$M,'data (1)'!$A:$A,XYZ!G$1,'data (1)'!$J:$J,XYZ!$A11) -> 0
A12: ПЕРЕКИСЬ ВОДОРОДА 3% 100МЛ. №1 Р-Р ДЕЗ.СР-ВО ФЛ. (НДС 20%) | B12: =_xlfn.STDEV.S(C12:G12)/AVERAGE(C12:G12) -> 0.88545111 | C12: =SUMIFS('data (1)'!$M:$M,'data (1)'!$A:$A,XYZ!C$1,'data (1)'!$J:$J,XYZ!$A12) -> 0 | D12: =SUMIFS('data (1)'!$M:$M,'data (1)'!$A:$A,XYZ!D$1,'data (1)'!$J:$J,XYZ!$A12) -> 5 | E12: =SUMIFS('data (1)'!$M:$M,'data (1)'!$A:$A,XYZ!E$1,'data (1)'!$J:$J,XYZ!$A12) -> 2 | F12: =SUMIFS('data (1)'!$M:$M,'data (1)'!$A:$A,XYZ!F$1,'data (1)'!$J:$J,XYZ!$A12) -> 1 | G12: =SUMIFS('data (1)'!$M:$M,'data (1)'!$A:$A,XYZ!G$1,'data (1)'!$J:$J,XYZ!$A12) -> 5
A13: ЛЕЙКОПЛАСТЫРЬ БАКТЕР. 6X10 №1 /ВЕРОФАРМ/ | B13: =_xlfn.STDEV.S(C13:G13)/AVERAGE(C13:G13) -> 1.6676526 | C13: =SUMIFS('data (1)'!$M:$M,'data (1)'!$A:$A,XYZ!C$1,'data (1)'!$J:$J,XYZ!$A13) -> 10 | D13: =SUMIFS('data (1)'!$M:$M,'data (1)'!$A:$A,XYZ!D$1,'data (1)'!$J:$J,XYZ!$A13) -> 0 | E13: =SUMIFS('data (1)'!$M:$M,'data (1)'!$A:$A,XYZ!E$1,'data (1)'!$J:$J,XYZ!$A13) -> 0 | F13: =SUMIFS('data (1)'!$M:$M,'data (1)'!$A:$A,XYZ!F$1,'data (1)'!$J:$J,XYZ!$A13) -> 3 | G13: =SUMIFS('data (1)'!$M:$M,'data (1)'!$A:$A,XYZ!G$1,'data (1)'!$J:$J,XYZ!$A13) -> 0
... A804: ХАРТМАНН КОСМОПОР Е ПОВЯЗКА 7,2Х5СМ №50 П/ОПЕР. САМОКЛ. СТЕР. /АРТ.9008705/ [HARTMANN COSMOPOR] | B804: =_xlfn.STDEV.S(C804:G804)/AVERAGE(C804:G804) -> 2.236068 | C804: =SUMIFS('data (1)'!$M:$M,'data (1)'!$A:$A,XYZ!C$1,'data (1)'!$J:$J,XYZ!$A804) -> 0 | D804: =SUMIFS('data (1)'!$M:$M,'data (1)'!$A:$A,XYZ!D$1,'data (1)'!$J:$J,XYZ!$A804) -> 0 | E804: =SUMIFS('data (1)'!$M:$M,'data (1)'!$A:$A,XYZ!E$1,'data (1)'!$J:$J,XYZ!$A804) -> 0 | F804: =SUMIFS('data (1)'!$M:$M,'data (1)'!$A:$A,XYZ!F$1,'data (1)'!$J:$J,XYZ!$A804) -> 0.04 | G804: =SUMIFS('data (1)'!$M:$M,'data (1)'!$A:$A,XYZ!G$1,'data (1)'!$J:$J,XYZ!$A804) -> 0
